sigma/pipelines/windows/__init__.py
sigma/pipelines/windows/windows.py
pysigma_pipeline_windows-1.2.0.dist-info/LICENSE
pysigma_pipeline_windows-1.2.0.dist-info/METADATA
pysigma_pipeline_windows-1.2.0.dist-info/WHEEL
pysigma_pipeline_windows-1.2.0.dist-info/RECORD
