Metadata-Version: 2.1
Name: pysigma-pipeline-windows
Version: 1.2.0
Summary: pySigma Windows processing pipelines
Home-page: https://github.com/SigmaHQ/pySigma-pipeline-windows
License: LGPL-2.1-only
Author: frack113
Author-email: frack113@users.noreply.github.com
Requires-Python: >=3.8,<4.0
Classifier: License :: OSI Approved
Classifier: Programming Language :: Python :: 3
Classifier: Programming Language :: Python :: 3.8
Classifier: Programming Language :: Python :: 3.9
Classifier: Programming Language :: Python :: 3.10
Classifier: Programming Language :: Python :: 3.11
Classifier: Programming Language :: Python :: 3.12
Requires-Dist: pysigma (>=0.11,<0.12)
Project-URL: Repository, https://github.com/SigmaHQ/pySigma-pipeline-windows
